CTkWidgets/__init__.py
CTkWidgets/ctkcalendar.py
CTkWidgets/ctkdateentry.py
CTKWidgets-1.0.0.dist-info/LICENSE
CTKWidgets-1.0.0.dist-info/METADATA
CTKWidgets-1.0.0.dist-info/WHEEL
CTKWidgets-1.0.0.dist-info/top_level.txt
CTKWidgets-1.0.0.dist-info/RECORD
