Metadata-Version: 2.1
Name: CTKWidgets
Version: 1.0.0
Summary: Uma biblioteca com widgets CTkCalendar e CTkDateEntry
Home-page: https://github.com/ClaudioM1386/CTkWidgets
Author: Claudio Morais
Author-email: jc.morais86@gmail.com
License: MIT
Classifier: Programming Language :: Python :: 3
Classifier: License :: OSI Approved :: MIT License
Classifier: Operating System :: OS Independent
Requires-Python: >=3.6
License-File: LICENSE
Requires-Dist: requests
